{
  "project_info": {
    "project_number": "525820102775",
    "project_id": "examen3pm1-0076",
    "storage_bucket": "examen3pm1-0076.appspot.com"
  },
  "client": [
    {
      "client_info": {
        "mobilesdk_app_id": "1:525820102775:android:7a9bbd9254bb67d893de72",
        "android_client_info": {
          "package_name": "com.example.examen3pm1_0076"
        }
      },
      "oauth_client": [],
      "api_key": [
        {
          "current_key": "AIzaSyBDWn0cBZo1EM41m83cr6tGrmjbSyCdWjU"
        }
      ],
      "services": {
        "appinvite_service": {
          "other_platform_oauth_client": []
        }
      }
    }
  ],
  "configuration_version": "1"
}